tunan_ground/__init__.py
tunan_ground/say_hello.py
tunan_ground/sys_path.py
tunan_ground-0.0.4.dist-info/LICENSE
tunan_ground-0.0.4.dist-info/METADATA
tunan_ground-0.0.4.dist-info/WHEEL
tunan_ground-0.0.4.dist-info/top_level.txt
tunan_ground-0.0.4.dist-info/RECORD
