Metadata-Version: 2.1
Name: tunan_ground
Version: 0.0.4
Summary: wutunan say hello
Author-email: wutunan <19970694323@163.com>
Classifier: Programming Language :: Python :: 3
Classifier: License :: OSI Approved :: MIT License
Classifier: Operating System :: OS Independent
Requires-Python: >=3.7
License-File: LICENSE
